{
    "key": "group_595a6c680c298",
    "title": "Options",
    "fields": [
        {
            "key": "field_595a6c8af7af3",
            "label": "General",
            "name": "",
            "type": "tab",
            "instructions": "",
            "required": 0,
            "conditional_logic": 0,
            "wrapper": {
                "width": "",
                "class": "",
                "id": ""
            },
            "placement": "left",
            "endpoint": 0
        },
        {
            "key": "field_5f401ec501904",
            "label": "Facebook",
            "name": "facebook",
            "type": "text",
            "instructions": "Enter your profile URL.",
            "required": 0,
            "conditional_logic": 0,
            "wrapper": {
                "width": "50",
                "class": "",
                "id": ""
            },
            "default_value": "",
            "placeholder": "",
            "prepend": "",
            "append": "",
            "maxlength": ""
        },
        {
            "key": "field_5f401ed501905",
            "label": "Instagram",
            "name": "instagram",
            "type": "text",
            "instructions": "Enter your profile URL.",
            "required": 0,
            "conditional_logic": 0,
            "wrapper": {
                "width": "50",
                "class": "",
                "id": ""
            },
            "default_value": "",
            "placeholder": "",
            "prepend": "",
            "append": "",
            "maxlength": ""
        },
        {
            "key": "field_595a6c92f7af4",
            "label": "Default Featured Image",
            "name": "default_featured_image",
            "type": "image",
            "instructions": "Upload your image. This will be used for all pages and posts that do not have a featured image.",
            "required": 0,
            "conditional_logic": 0,
            "wrapper": {
                "width": "",
                "class": "",
                "id": ""
            },
            "return_format": "url",
            "preview_size": "large",
            "library": "all",
            "min_width": "",
            "min_height": "",
            "min_size": "",
            "max_width": "",
            "max_height": "",
            "max_size": "",
            "mime_types": ""
        },
        {
            "key": "field_5f401ef701906",
            "label": "Blog",
            "name": "",
            "type": "tab",
            "instructions": "",
            "required": 0,
            "conditional_logic": 0,
            "wrapper": {
                "width": "",
                "class": "",
                "id": ""
            },
            "placement": "left",
            "endpoint": 0
        },
        {
            "key": "field_5f401f0301908",
            "label": "Blog Title",
            "name": "blog_title",
            "type": "text",
            "instructions": "Enter a title.",
            "required": 0,
            "conditional_logic": 0,
            "wrapper": {
                "width": "50",
                "class": "",
                "id": ""
            },
            "default_value": "",
            "placeholder": "",
            "prepend": "",
            "append": "",
            "maxlength": ""
        },
        {
            "key": "field_5f401f1201909",
            "label": "Blog Optional H1",
            "name": "blog_optional_h1",
            "type": "text",
            "instructions": "Enter an optional h1.",
            "required": 0,
            "conditional_logic": 0,
            "wrapper": {
                "width": "50",
                "class": "",
                "id": ""
            },
            "default_value": "",
            "placeholder": "",
            "prepend": "",
            "append": "",
            "maxlength": ""
        },
        {
            "key": "field_5f401f1f0190a",
            "label": "CTA Title",
            "name": "cta_title",
            "type": "text",
            "instructions": "Enter a title.",
            "required": 0,
            "conditional_logic": 0,
            "wrapper": {
                "width": "50",
                "class": "",
                "id": ""
            },
            "default_value": "",
            "placeholder": "",
            "prepend": "",
            "append": "",
            "maxlength": ""
        },
        {
            "key": "field_5f401f290190b",
            "label": "CTA Button",
            "name": "cta_button",
            "type": "link",
            "instructions": "Setup your button.",
            "required": 0,
            "conditional_logic": 0,
            "wrapper": {
                "width": "50",
                "class": "",
                "id": ""
            },
            "return_format": "array"
        },
        {
            "key": "field_5f401f310190c",
            "label": "CTA Text",
            "name": "cta_text",
            "type": "textarea",
            "instructions": "Enter your text.",
            "required": 0,
            "conditional_logic": 0,
            "wrapper": {
                "width": "50",
                "class": "",
                "id": ""
            },
            "default_value": "",
            "placeholder": "",
            "maxlength": "",
            "rows": 4,
            "new_lines": "br"
        },
        {
            "key": "field_5f401f430190d",
            "label": "CTA Image",
            "name": "cta_image",
            "type": "image",
            "instructions": "Upload your image.",
            "required": 0,
            "conditional_logic": 0,
            "wrapper": {
                "width": "50",
                "class": "",
                "id": ""
            },
            "return_format": "url",
            "preview_size": "medium",
            "library": "all",
            "min_width": "",
            "min_height": "",
            "min_size": "",
            "max_width": "",
            "max_height": "",
            "max_size": "",
            "mime_types": ""
        },
        {
            "key": "field_5b295d26eeafe",
            "label": "Code & SEO",
            "name": "",
            "type": "tab",
            "instructions": "",
            "required": 0,
            "conditional_logic": 0,
            "wrapper": {
                "width": "",
                "class": "",
                "id": ""
            },
            "placement": "left",
            "endpoint": 0
        },
        {
            "key": "field_5b295d34eeaff",
            "label": "Logo Title",
            "name": "logo_title",
            "type": "text",
            "instructions": "Enter a title that will be applied to the logo.",
            "required": 0,
            "conditional_logic": 0,
            "wrapper": {
                "width": "50",
                "class": "",
                "id": ""
            },
            "default_value": "",
            "placeholder": "",
            "prepend": "",
            "append": "",
            "maxlength": ""
        },
        {
            "key": "field_5b295d4beeb00",
            "label": "Logo Alt Text",
            "name": "logo_alt_text",
            "type": "text",
            "instructions": "Enter alt text that will be applied to the logo.",
            "required": 0,
            "conditional_logic": 0,
            "wrapper": {
                "width": "50",
                "class": "",
                "id": ""
            },
            "default_value": "",
            "placeholder": "",
            "prepend": "",
            "append": "",
            "maxlength": ""
        },
        {
            "key": "field_5b295d6beeb01",
            "label": "Header Scripts",
            "name": "header_scripts",
            "type": "textarea",
            "instructions": "Enter any scripts that need to be placed in the head of the website.",
            "required": 0,
            "conditional_logic": 0,
            "wrapper": {
                "width": "",
                "class": "",
                "id": ""
            },
            "default_value": "",
            "placeholder": "",
            "maxlength": "",
            "rows": "",
            "new_lines": ""
        },
        {
            "key": "field_5b295d83eeb02",
            "label": "Body Scripts",
            "name": "body_scripts",
            "type": "textarea",
            "instructions": "Enter any scripts that need to be placed right after the opening of the body tag.",
            "required": 0,
            "conditional_logic": 0,
            "wrapper": {
                "width": "",
                "class": "",
                "id": ""
            },
            "default_value": "",
            "placeholder": "",
            "maxlength": "",
            "rows": "",
            "new_lines": ""
        },
        {
            "key": "field_5b295d99eeb03",
            "label": "Footer Scripts",
            "name": "footer_scripts",
            "type": "textarea",
            "instructions": "Enter any scripts that need to be placed right before the closing of the body tag.",
            "required": 0,
            "conditional_logic": 0,
            "wrapper": {
                "width": "",
                "class": "",
                "id": ""
            },
            "default_value": "",
            "placeholder": "",
            "maxlength": "",
            "rows": "",
            "new_lines": ""
        },
        {
            "key": "field_5b295daeeeb04",
            "label": "Custom CSS",
            "name": "custom_css",
            "type": "textarea",
            "instructions": "Enter any custom CSS needed for this website.",
            "required": 0,
            "conditional_logic": 0,
            "wrapper": {
                "width": "",
                "class": "",
                "id": ""
            },
            "default_value": "",
            "placeholder": "",
            "maxlength": "",
            "rows": "",
            "new_lines": ""
        }
    ],
    "location": [
        [
            {
                "param": "options_page",
                "operator": "==",
                "value": "acf-options"
            }
        ]
    ],
    "menu_order": 0,
    "position": "normal",
    "style": "default",
    "label_placement": "top",
    "instruction_placement": "label",
    "hide_on_screen": "",
    "active": true,
    "description": "",
    "modified": 1598037844
}